pypbireport/__init__.py
pypbireport/constants/bookmarks.py
pypbireport/constants/charts.py
pypbireport/constants/dax_code.py
pypbireport/constants/shapes.py
pypbireport/constants/structures.py
pypbireport/functions/functions.py
pypbireport/functions/pprlist.py
pypbireport/ms_dll_scripts/Microsoft.AnalysisServices.AdomdClient.dll
pypbireport/ms_dll_scripts/Microsoft.AnalysisServices.AdomdClient.resources.dll
pypbireport/ms_dll_scripts/Microsoft.AnalysisServices.Core.dll
pypbireport/ms_dll_scripts/Microsoft.AnalysisServices.Core.resources.dll
pypbireport/ms_dll_scripts/Microsoft.AnalysisServices.SPClient.Interfaces.dll
pypbireport/ms_dll_scripts/Microsoft.AnalysisServices.Tabular.Json.dll
pypbireport/ms_dll_scripts/Microsoft.AnalysisServices.Tabular.Tmdl.dll
pypbireport/ms_dll_scripts/Microsoft.AnalysisServices.Tabular.dll
pypbireport/ms_dll_scripts/Microsoft.AnalysisServices.Tabular.resources.dll
pypbireport/ms_dll_scripts/Microsoft.AnalysisServices.resources.dll
pypbireport/ms_dll_scripts/Microsoft.Identity.Client.dll
pypbireport/ms_dll_scripts/Microsoft.IdentityModel.Abstractions.dll
pypbireport/ms_dll_scripts/ModernWpf.Controls.resources.dll
pypbireport/ms_dll_scripts/ModernWpf.resources.dll
pypbireport/ms_dll_scripts/System.Net.Http.dll
pypbireport/ms_dll_scripts/System.ValueTuple.dll
pypbireport/ms_dll_scripts/UnitComboLib.resources.dll
pypbireport/ms_dll_scripts/get_open_reports.ps1
pypbireport/pbi/pbibookmark.py
pypbireport/pbi/pbifile.py
pypbireport/pbi/pbimodel.py
pypbireport/pbi/pbireport.py
pypbireport/pbi/pbivisual.py
pypbireport/visuals/preset_attrs.py
pypbireport/visuals/visuals_attrs.py
pypbireport-0.2.4.dist-info/licenses/LICENSE
pypbireport-0.2.4.dist-info/METADATA
pypbireport-0.2.4.dist-info/WHEEL
pypbireport-0.2.4.dist-info/top_level.txt
pypbireport-0.2.4.dist-info/RECORD
