Metadata-Version: 2.4
Name: pypbireport
Version: 0.2.4
Summary: Package to manipulate Power BI report and model
Author-email: Ismael Miranda <ismaelmiranda11@hotmail.com>
Project-URL: repository, https://github.com/IsmaelMiranda11/py-powerbi-report
Project-URL: documentation, https://py-powerbi-report.readthedocs.io/en/latest/index.html
Classifier: Programming Language :: Python :: 3
Classifier: License :: OSI Approved :: MIT License
Classifier: Operating System :: Microsoft :: Windows :: Windows 10
Requires-Python: >=3.9
License-File: LICENSE
Requires-Dist: pandas>=2
Requires-Dist: pyyaml>=6
Requires-Dist: jsonpath-ng>=1.5.3
Requires-Dist: pythonnet>=3.0.2
Requires-Dist: Unidecode>=1.3.6
Requires-Dist: openpyxl>=3
Requires-Dist: xlsxwriter
Dynamic: license-file
